ysgrpctelemetry/__init__.py
ysgrpctelemetry/_version.py
ysgrpctelemetry/apps.py
ysgrpctelemetry/grpctelemetry.py
ysgrpctelemetry/protoparse.py
ysgrpctelemetry/urls.py
ysgrpctelemetry/views.py
ysgrpctelemetry/generated/__init__.py
ysgrpctelemetry/generated/mdt_grpc_dialout_pb2.py
ysgrpctelemetry/generated/mdt_grpc_dialout_pb2_grpc.py
ysgrpctelemetry/generated/telemetry_pb2.py
ysgrpctelemetry/generated/telemetry_pb2_grpc.py
ysgrpctelemetry/static/ysgrpctelemetry/css/grpctelemetry.css
ysgrpctelemetry/static/ysgrpctelemetry/docs/.buildinfo
ysgrpctelemetry/static/ysgrpctelemetry/docs/clear.fjson
ysgrpctelemetry/static/ysgrpctelemetry/docs/clear.html
ysgrpctelemetry/static/ysgrpctelemetry/docs/environment.pickle
ysgrpctelemetry/static/ysgrpctelemetry/docs/genindex.fjson
ysgrpctelemetry/static/ysgrpctelemetry/docs/genindex.html
ysgrpctelemetry/static/ysgrpctelemetry/docs/globalcontext.json
ysgrpctelemetry/static/ysgrpctelemetry/docs/grpc.fjson
ysgrpctelemetry/static/ysgrpctelemetry/docs/grpc.html
ysgrpctelemetry/static/ysgrpctelemetry/docs/index.fjson
ysgrpctelemetry/static/ysgrpctelemetry/docs/index.html
ysgrpctelemetry/static/ysgrpctelemetry/docs/last_build
ysgrpctelemetry/static/ysgrpctelemetry/docs/objects.inv
ysgrpctelemetry/static/ysgrpctelemetry/docs/search.fjson
ysgrpctelemetry/static/ysgrpctelemetry/docs/search.html
ysgrpctelemetry/static/ysgrpctelemetry/docs/searchindex.js
ysgrpctelemetry/static/ysgrpctelemetry/docs/searchindex.json
ysgrpctelemetry/static/ysgrpctelemetry/docs/tls.fjson
ysgrpctelemetry/static/ysgrpctelemetry/docs/tls.html
ysgrpctelemetry/static/ysgrpctelemetry/docs/.doctrees/clear.doctree
ysgrpctelemetry/static/ysgrpctelemetry/docs/.doctrees/environment.pickle
ysgrpctelemetry/static/ysgrpctelemetry/docs/.doctrees/grpc.doctree
ysgrpctelemetry/static/ysgrpctelemetry/docs/.doctrees/index.doctree
ysgrpctelemetry/static/ysgrpctelemetry/docs/.doctrees/tls.doctree
ysgrpctelemetry/static/ysgrpctelemetry/docs/_images/clear-channel.png
yangsuite_grpc_telemetry-1.0.9.dist-info/LICENSE.txt
yangsuite_grpc_telemetry-1.0.9.dist-info/METADATA
yangsuite_grpc_telemetry-1.0.9.dist-info/WHEEL
yangsuite_grpc_telemetry-1.0.9.dist-info/entry_points.txt
yangsuite_grpc_telemetry-1.0.9.dist-info/top_level.txt
yangsuite_grpc_telemetry-1.0.9.dist-info/RECORD
